README.md
setup.py
fastpython/fastpython.py
fastpython/test.py
fastpython.egg-info/PKG-INFO
fastpython.egg-info/SOURCES.txt
fastpython.egg-info/dependency_links.txt
fastpython.egg-info/top_level.txt