Metadata-Version: 2.1
Name: fastpython
Version: 1.2.0
Author: MaxymPlayz
